form/__init__.py
form/datapath.py
form/formlink.py
form/init.frm
form/ioutil.py
form/py.typed
form/six.py
python_form-0.2.3.dist-info/LICENCE.md
python_form-0.2.3.dist-info/METADATA
python_form-0.2.3.dist-info/WHEEL
python_form-0.2.3.dist-info/top_level.txt
python_form-0.2.3.dist-info/RECORD
